khivefields/__init__.py
khivefields/action.py
khivefields/code.py
khivefields/file.py
khivefields/instruct.py
khivefields/reason.py
khivefields/research.py
khivefields/version.py
khivefields/common/__init__.py
khivefields/common/models.py
khivefields/common/snippet.py
khivefields/common/source.py
khivefields/utils/__init__.py
khivefields/utils/breakdown_pydantic.py
khivefields/utils/create_path.py
khivefields/utils/current_timestamp.py
khivefields/utils/extract_json.py
khivefields/utils/fuzzy_parse_json.py
khivefields/utils/hash_dict.py
khivefields/utils/parse_xml.py
khivefields/utils/to_dict.py
khivefields/utils/to_list.py
khivefields/utils/to_num.py
khivefields-0.1.2.dist-info/METADATA
khivefields-0.1.2.dist-info/WHEEL
khivefields-0.1.2.dist-info/licenses/LICENSE
khivefields-0.1.2.dist-info/RECORD
